<?xml version="1.0" encoding="UTF-8" ?>

<!DOCTYPE struts PUBLIC
    "-//Apache Software Foundation//DTD Struts Configuration 2.5//EN"
    "http://struts.apache.org/dtds/struts-2.5.dtd">
<struts>

<!-- 商品的操作对象 -->
<package name="Commodity" namespace="/Commodity" extends="struts-default">
<action name="Commodity_*" class="CommodityAction" method="{1}">
<result name="findAll">/Commodity/ShowCommodity.jsp</result>
<result name="add_success" type="chain">Commodity_findAll</result>
<result name="delete_success" type="chain">Commodity_findAll</result>
<result name="update_success">/Commodity/UpdateCommodity.jsp</result>
<result name="save_success" type="chain">Commodity_findAll</result>
<result name="input">/index.jsp</result>
<allowed-methods>deleteCommodity,addCommodity,saveCommodity,UpdateCommodity,findAll</allowed-methods>
</action>
</package>

<!-- 员工的对象 -->
<package name="Employee" namespace="/Employee" extends="struts-default">
<!-- 定义了自己的拦截器之后，不会调用系统默认的拦截器，需要自己添加 -->
<interceptors >
<interceptor name="loginInterceptor" class="com.ssh.money.LoginInterceptors"></interceptor>

<!-- 定义自己的拦截栈，按照栈的顺序执行拦截作用 -->
<interceptor-stack name="myInterceptor">
<interceptor-ref name="defaultStack"></interceptor-ref>
<interceptor-ref name="loginInterceptor"></interceptor-ref>
</interceptor-stack>
</interceptors>
<!-- 默认拦截器配置 -->
<default-interceptor-ref name="myInterceptor"></default-interceptor-ref>
<action name="Employee_*" class="EmployeeAction" method="{1}">
<result name="query_list">/Employee/showEmployee.jsp</result>
<result name="delete_success" type="chain">Employee_findAll</result>
<result name="update_success">/Employee/EmployeeUpdate.jsp</result>
<result name="save_success" type="chain">Employee_findAll</result>
<result name="add_success" type="chain">Employee_findAll</result>
<allowed-methods>findAll,delete,addEmployee,findByid,Update,save</allowed-methods>
</action>
</package>
<constant name="struts.enable.DynamicMethodInvocation" value="true" />

</struts>